{
	"configurations" : 
	[
		{
			"directories" : 
			[
				{
					"build" : ".",
					"hasInstallRule" : true,
					"jsonFile" : "directory-.-433e6f24dfa0a339f8f0.json",
					"minimumCMakeVersion" : 
					{
						"string" : "3.15"
					},
					"projectIndex" : 0,
					"source" : ".",
					"targetIndexes" : 
					[
						0,
						1,
						2,
						3
					]
				}
			],
			"name" : "",
			"projects" : 
			[
				{
					"directoryIndexes" : 
					[
						0
					],
					"name" : "kobuki_bumper2pc",
					"targetIndexes" : 
					[
						0,
						1,
						2,
						3
					]
				}
			],
			"targets" : 
			[
				{
					"directoryIndex" : 0,
					"id" : "kobuki_bumper2pc::@6890427a1f51a3e7e1df",
					"jsonFile" : "target-kobuki_bumper2pc-1b514190032b16cbb501.json",
					"name" : "kobuki_bumper2pc",
					"projectIndex" : 0
				},
				{
					"directoryIndex" : 0,
					"id" : "kobuki_bumper2pc_node::@6890427a1f51a3e7e1df",
					"jsonFile" : "target-kobuki_bumper2pc_node-090ae6e7c3e44083fd39.json",
					"name" : "kobuki_bumper2pc_node",
					"projectIndex" : 0
				},
				{
					"directoryIndex" : 0,
					"id" : "kobuki_bumper2pc_uninstall::@6890427a1f51a3e7e1df",
					"jsonFile" : "target-kobuki_bumper2pc_uninstall-410a9c3cdfc2665e435d.json",
					"name" : "kobuki_bumper2pc_uninstall",
					"projectIndex" : 0
				},
				{
					"directoryIndex" : 0,
					"id" : "uninstall::@6890427a1f51a3e7e1df",
					"jsonFile" : "target-uninstall-8f3c07257e8a88ce269e.json",
					"name" : "uninstall",
					"projectIndex" : 0
				}
			]
		}
	],
	"kind" : "codemodel",
	"paths" : 
	{
		"build" : "/home/abdulrafi/Desktop/ROS2_Final_Project/kobuki_ws/build/kobuki_bumper2pc",
		"source" : "/home/abdulrafi/Desktop/ROS2_Final_Project/kobuki_ws/src/ThirdParty/kobuki_ros/kobuki_bumper2pc"
	},
	"version" : 
	{
		"major" : 2,
		"minor" : 6
	}
}
