{
  "type_description_msg": {
    "type_description": {
      "type_name": "astra_camera_msgs/srv/GetString_Response",
      "fields": [
        {
          "name": "data",
          "type": {
            "type_id": 17,
            "capacity": 0,
            "string_capacity": 0,
            "nested_type_name": ""
          },
          "default_value": ""
        },
        {
          "name": "success",
          "type": {
            "type_id": 15,
            "capacity": 0,
            "string_capacity": 0,
            "nested_type_name": ""
          },
          "default_value": ""
        },
        {
          "name": "message",
          "type": {
            "type_id": 17,
            "capacity": 0,
            "string_capacity": 0,
            "nested_type_name": ""
          },
          "default_value": ""
        }
      ]
    },
    "referenced_type_descriptions": []
  },
  "type_hashes": [
    {
      "type_name": "astra_camera_msgs/srv/GetString_Response",
      "hash_string": "RIHS01_329c6b73fed71ea59a131d21c5fa604a72e88e6c684ac323e71c7142eaf560df"
    }
  ]
}